Workbook

Sheet Inputs
B2: Description | C2: Value | D2: Unit | E2: Abbreviation Meaning | F2: Source (Where to find it)
B3: Project Capacity | C3: 792 | D3: kWp | E3: Kilowatt Peak: The maximum power the system generates at standard test conditions. | F3: HelioScope PDF: Look for "System Size" or "Nameplate Capacity".
B4: Specific Yield | C4: 1540 | D4: kWh/kWp | E4: Kilowatt-hours per kWp: How efficient the system is. (Calculation: Annual Production / Project Capacity). | F4: HelioScope PDF: Look for "Yield" or calculate it yourself.
B5: Year 1 Production | C5: 1220000 | D5: kWh | E5: Kilowatt-hours: Total energy generated in the first year. | F5: HelioScope PDF: Look for "Annual Production".
B6: CAPEX (Total Cost) | C6: 3000000000 | D6: COP | E6: Capital Expenditure: The total price to build the project. | F6: Estimation: Since this is a portfolio project, assume approx. $3,000,000 COP per Watt installed.
B7: Current Energy Tariff | C7: 800 | D7: COP/kWh | E7: Cost of Energy: How much the client currently pays the grid (Enel/EPM) for 1 unit of energy. | F7: Utility Bill: Usually found on the client's monthly electricity bill. (Use 800 as a market average).
B8: Energy Inflation | C8: 0.05 | D8: % | E8: CPI (Consumer Price Index): How much energy prices rise each year. | F8: Internet: Google "Colombia energy inflation history" (5-7% is standard).
B9: System Degradation | C9: 0.005 | D9: % | E9: Wear & Tear: Solar panels lose efficiency over time. | F9: Datasheet: Standard for Tier 1 panels is 0.4% to 0.5% loss per year.
B10: O&M Cost | C10: 0.012 | D10: % of CAPEX | E10: Operations & Maintenance: Cleaning panels, fixing wires, etc. | F10: Industry Standard: Usually 1% of the total project cost per year.

Sheet Cash Flow
B2: Year | C2: Energy Yield (kWh) | D2: Tariff Rate (COP/kWh) | E2: Operational Savings | F2: O&M Expenses (Costs) | G2: Net Cash Flow | H2: Cumulative Cash Flow
B3: 0 | G3: =-Inputs!C6 -> -3000000000 | H3: =G3 -> -3000000000
B4: 1 | C4: =Inputs!C5 -> 1220000 | D4: =Inputs!C7 -> 800 | E4: =C4*D4 -> 976000000 | F4: =Inputs!$C$6*Inputs!$C$10 -> 36000000 | G4: =E4-F4 -> 940000000 | H4: =H3+G4 -> -2060000000
B5: 2 | C5: =C4 *(1-Inputs!$C$9) -> 1213900 | D5: =D4*(1+Inputs!$C$8) -> 840 | E5: =C5*D5 -> 1019676000 | F5: =Inputs!$C$6*Inputs!$C$10 -> 36000000 | G5: =E5-F5 -> 983676000 | H5: =H4+G5 -> -1076324000
B6: 3 | C6: =C5 *(1-Inputs!$C$9) -> 1207830.5 | D6: =D5*(1+Inputs!$C$8) -> 882 | E6: =C6*D6 -> 1065306501 | F6: =Inputs!$C$6*Inputs!$C$10 -> 36000000 | G6: =E6-F6 -> 1029306501 | H6: =H5+G6 -> -47017499
B7: 4 | C7: =C6 *(1-Inputs!$C$9) -> 1201791.3 | D7: =D6*(1+Inputs!$C$8) -> 926.1 | E7: =C7*D7 -> 1.112979e+09 | F7: =Inputs!$C$6*Inputs!$C$10 -> 36000000 | G7: =E7-F7 -> 1.076979e+09 | H7: =H6+G7 -> 1.0299615e+09
B8: 5 | C8: =C7 *(1-Inputs!$C$9) -> 1195782.4 | D8: =D7*(1+Inputs!$C$8) -> 972.405 | E8: =C8*D8 -> 1.1627848e+09 | F8: =Inputs!$C$6*Inputs!$C$10 -> 36000000 | G8: =E8-F8 -> 1.1267848e+09 | H8: =H7+G8 -> 2.1567462e+09
B9: 6 | C9: =C8 *(1-Inputs!$C$9) -> 1189803.5 | D9: =D8*(1+Inputs!$C$8) -> 1021.0253 | E9: =C9*D9 -> 1.2148194e+09 | F9: =Inputs!$C$6*Inputs!$C$10 -> 36000000 | G9: =E9-F9 -> 1.1788194e+09 | H9: =H8+G9 -> 3.3355656e+09
B10: 7 | C10: =C9 *(1-Inputs!$C$9) -> 1183854.5 | D10: =D9*(1+Inputs!$C$8) -> 1072.0765 | E10: =C10*D10 -> 1.2691826e+09 | F10: =Inputs!$C$6*Inputs!$C$10 -> 36000000 | G10: =E10-F10 -> 1.2331826e+09 | H10: =H9+G10 -> 4.5687482e+09
B11: 8 | C11: =C10 *(1-Inputs!$C$9) -> 1177935.2 | D11: =D10*(1+Inputs!$C$8) -> 1125.6803 | E11: =C11*D11 -> 1.3259785e+09 | F11: =Inputs!$C$6*Inputs!$C$10 -> 36000000 | G11: =E11-F11 -> 1.2899785e+09 | H11: =H10+G11 -> 5.8587267e+09
B12: 9 | C12: =C11 *(1-Inputs!$C$9) -> 1172045.5 | D12: =D11*(1+Inputs!$C$8) -> 1181.9644 | E12: =C12*D12 -> 1.385316e+09 | F12: =Inputs!$C$6*Inputs!$C$10 -> 36000000 | G12: =E12-F12 -> 1.349316e+09 | H12: =H11+G12 -> 7.2080427e+09
B13: 10 | C13: =C12 *(1-Inputs!$C$9) -> 1166185.3 | D13: =D12*(1+Inputs!$C$8) -> 1241.0626 | E13: =C13*D13 -> 1.4473089e+09 | F13: =Inputs!$C$6*Inputs!$C$10 -> 36000000 | G13: =E13-F13 -> 1.4113089e+09 | H13: =H12+G13 -> 8.6193516e+09
B14: 11 | C14: =C13 *(1-Inputs!$C$9) -> 1160354.4 | D14: =D13*(1+Inputs!$C$8) -> 1303.1157 | E14: =C14*D14 -> 1.512076e+09 | F14: =Inputs!$C$6*Inputs!$C$10 -> 36000000 | G14: =E14-F14 -> 1.476076e+09 | H14: =H13+G14 -> 1.0095428e+10
B15: 12 | C15: =C14 *(1-Inputs!$C$9) -> 1154552.6 | D15: =D14*(1+Inputs!$C$8) -> 1368.2715 | E15: =C15*D15 -> 1.5797414e+09 | F15: =Inputs!$C$6*Inputs!$C$10 -> 36000000 | G15: =E15-F15 -> 1.5437414e+09 | H15: =H14+G15 -> 1.1639169e+10
B16: 13 | C16: =C15 *(1-Inputs!$C$9) -> 1148779.8 | D16: =D15*(1+Inputs!$C$8) -> 1436.6851 | E16: =C16*D16 -> 1.6504348e+09 | F16: =Inputs!$C$6*Inputs!$C$10 -> 36000000 | G16: =E16-F16 -> 1.6144348e+09 | H16: =H15+G16 -> 1.3253604e+10
... B28: 25 | C28: =C27 *(1-Inputs!$C$9) -> 1081717.3 | D28: =D27*(1+Inputs!$C$8) -> 2580.08 | E28: =C28*D28 -> 2.7909171e+09 | F28: =Inputs!$C$6*Inputs!$C$10 -> 36000000 | G28: =E28-F28 -> 2.7549171e+09 | H28: =H27+G28 -> 3.9447723e+10

Sheet Dashborad
C2: KPI
B3: Years | C3: Total Lifetime Savings | D3: Payback Periods (Years) | E3: ROI
B4: 25 | C4: =SUM('Cash Flow'!G:G) -> 3.9447723e+10 | D4: =COUNTIF('Cash Flow'!H:H, "<0") -> 4 | E4: =('Cash Flow'!H28)/Inputs!$C$6 -> 13.149241
B5: 20 | C5: =SUM('Cash Flow'!G3:G23) -> 2.681846e+10 | E5: =('Cash Flow'!H23)/Inputs!$C$6 -> 8.9394867
B6: 15 | C6: =SUM('Cash Flow'!G3:G18) -> 1.6707349e+10 | E6: =('Cash Flow'!H18)/Inputs!$C$6 -> 5.5691165
B7: 10 | C7: =SUM('Cash Flow'!G3:G13) -> 8.6193516e+09 | E7: =('Cash Flow'!H13)/Inputs!$C$6 -> 2.8731172
B8: 5 | C8: =SUM('Cash Flow'!G3:G8) -> 2.1567462e+09 | E8: =('Cash Flow'!H8)/Inputs!$C$6 -> 0.71891541
